{"error":"Fehler","errors":"Fehler","loading":"Wird geladen","and":"und","isrequired":"ist erforderlich","arerequired":"sind erforderlich","selectcategory":"Kategorie auswählen","documentbannerpreview":"Vorschau des Dokumentenbanners","portalitemrequired":"Portal-Element ist erforderlich.","userconfigurepermissionrequired":"Benutzer-Konfigurationsberechtigung ist erforderlich.","missingclassificationschema":"Im Portal fehlt ein Klassifizierungsschema.","anerroroccurred":"Ein Fehler ist aufgetreten.","bannererror":"Einige Felder sind unvollständig oder enthalten Fehler. Details sind den hervorgehobenen Feldern zu entnehmen."}