{"error":"fejl","errors":"fejl","loading":"indlæser","and":"og","isrequired":"er påkrævet","arerequired":"er påkrævet","selectcategory":"vælg kategori","documentbannerpreview":"Eksempelvisning af dokumentbanner","portalitemrequired":"Portalelement er påkrævet.","userconfigurepermissionrequired":"Tilladelse til brugerkonfiguration er påkrævet.","missingclassificationschema":"Portal mangler klassifikationsskema.","anerroroccurred":"Der er opstået en fejl.","bannererror":"Visse felter er ikke kompatible eller indeholder fejl. Kontrollér de fremhævede felter for at få flere oplysninger."}