{"sketches":"Vázlatos vektoros elemek","actions":"Műveletek","edit":"Szerkesztés","duplicate":"Duplikált","featureDuplicated":"A kiválasztott vektoros elem másolása sikerült.","featuresDuplicated":"A kiválasztott vektoros elemek másolása sikerült.","copyToNewSketchLayer":"Másolás új Vázlat rétegre","delete":"Törlés","addSketch":"Vektoros elem hozzáadása","textPreview":"A","point":"Pont","line":"Vonal","polygon":"Sokszög","text":"Szöveg","collapse":"Összecsukás","expand":"Kibontás","saveWarning":"Ez a térkép nem mentett módosításokat tartalmaz a vázlat vektoros elemein. Mentse el a vázlatréteg-elemet, hogy a vázlat vektoros elemeit az elemmel együtt mentse.","learnMore":"További információ"}