{"units":{"FOOT":"picior","FEET":"ft","FOOT_TITLE":"Ft","FOOT_ABBR":"ft","FOOT_UNITS":"ft","YARD":"yard","YARDS":"yarzi","YARD_TITLE":"Iarzi","YARD_ABBR":"yd","YARD_UNITS":"yarzi","METER":"metru","METERS":"metri","METER_TITLE":"Metri","METER_ABBR":"m","METER_UNITS":"metri","KILOMETER":"kilometru","KILOMETERS":"kilometri","KILOMETER_TITLE":"Kilometri","KILOMETER_ABBR":"km","KILOMETER_UNITS":"km","MILE":"milă","MILES":"mile","MILE_TITLE":"Mile","MILE_ABBR":"mi.","MILE_UNITS":"mile","NAUTICAL_MILE":"milă nautică","NAUTICAL_MILES":"mile marine","NAUTICAL_MILE_TITLE":"Mile marine","NAUTICAL_MILE_ABBR":"nmi","NAUTICAL_MILE_UNITS":"nmi","SECOND":"secundă","SECONDS":"secunde","SECOND_TITLE":"Secunde","SECOND_ABBR":"s","SECOND_UNITS":"secunde","MINUTE":"minut","MINUTES":"minute","MINUTE_TITLE":"Minute","MINUTE_ABBR":"min.","MINUTE_UNITS":"minute","HOUR":"oră","HOURS":"ore","HOUR_TITLE":"Ore","HOUR_ABBR":"h","HOUR_UNITS":"ore","SQUARE_FOOT":"picior pătrat","SQUARE_FEET":"picioare pătrate","SQUARE_FOOT_TITLE":"Picioare pătrate","SQUARE_FOOT_ABBR":"ft. păt","SQUARE_FOOT_UNITS":"Picioare păt.","SQUARE_YARD":"yard pătrat","SQUARE_YARDS":"yarzi pătrați","SQUARE_YARD_TITLE":"Yarzi pătrați","SQUARE_YARD_ABBR":"yar. pătrat","SQUARE_YARD_UNITS":"yar. pătrați","SQUARE_METER":"metru pătrat","SQUARE_METERS":"metri pătrați","SQUARE_METER_TITLE":"Metri pătrați","SQUARE_METER_ABBR":"m2","SQUARE_METER_UNITS":"m2","SQUARE_KILOMETER":"kilometru pătrat","SQUARE_KILOMETERS":"kilometri pătrați","SQUARE_KILOMETER_TITLE":"Kilometri pătrați","SQUARE_KILOMETER_ABBR":"km2","SQUARE_KILOMETER_UNITS":"km2","SQUARE_MILE":"milă pătrată","SQUARE_MILES":"mile pătrate","SQUARE_MILE_TITLE":"Mile pătrate","SQUARE_MILE_ABBR":"mi2","SQUARE_MILE_UNITS":"mile2","ACRE":"acru","ACRES":"acri","ACRE_TITLE":"Acri","ACRE_ABBR":"ac","ACRE_UNITS":"acri","HECTARE":"hectar","HECTARES":"hectare","HECTARE_TITLE":"Hectare","HECTARE_ABBR":"ha","HECTARE_UNITS":"ha"},"variables":{"standardSource":"Date standard","customSource":"Date particularizate","layersSource":"Date despre straturi tematice","averageShort":"Med.","labelWithType":"${label} (${type})","count":"Număr","index":"Index","percent":"Procentaj","average":"Medie","median":"Mediană","percapita":"pe cap de locuitor","density":"Densitate","rate":"Evaluare","ratio":"Raport","reliability":"Fiabilitate","text":"Text","area":"Suprafaţă","segmentation":"Segmentare"}}