{"units":{"FOOT":"фут","FEET":"фута","FOOT_TITLE":"Фута","FOOT_ABBR":"фут","FOOT_UNITS":"фута","YARD":"ярд","YARDS":"ярда","YARD_TITLE":"Ярда","YARD_ABBR":"ярд","YARD_UNITS":"ярда","METER":"метър","METERS":"метри","METER_TITLE":"Метри","METER_ABBR":"м","METER_UNITS":"метри","KILOMETER":"километър","KILOMETERS":"километри","KILOMETER_TITLE":"Километри","KILOMETER_ABBR":"км","KILOMETER_UNITS":"км","MILE":"миля","MILES":"мили","MILE_TITLE":"Мили","MILE_ABBR":"миля","MILE_UNITS":"мили","NAUTICAL_MILE":"морска миля","NAUTICAL_MILES":"морски мили","NAUTICAL_MILE_TITLE":"Морски мили","NAUTICAL_MILE_ABBR":"морска миля","NAUTICAL_MILE_UNITS":"морска миля","SECOND":"секунда","SECONDS":"секунди","SECOND_TITLE":"Секунди","SECOND_ABBR":"сек","SECOND_UNITS":"секунди","MINUTE":"минута","MINUTES":"минути","MINUTE_TITLE":"Минути","MINUTE_ABBR":"мин","MINUTE_UNITS":"минути","HOUR":"час","HOURS":"часове","HOUR_TITLE":"Часове","HOUR_ABBR":"ч","HOUR_UNITS":"часове","SQUARE_FOOT":"квадратен фут","SQUARE_FEET":"квадратни фута","SQUARE_FOOT_TITLE":"Квадратни фута","SQUARE_FOOT_ABBR":"кв. фут","SQUARE_FOOT_UNITS":"кв. фута","SQUARE_YARD":"квадратен ярд","SQUARE_YARDS":"квадратни ярда","SQUARE_YARD_TITLE":"Квадратни ярда","SQUARE_YARD_ABBR":"кв. ярд","SQUARE_YARD_UNITS":"кв. ярда","SQUARE_METER":"квадратен метър","SQUARE_METERS":"квадратни метри","SQUARE_METER_TITLE":"Квадратни метри","SQUARE_METER_ABBR":"кв. м","SQUARE_METER_UNITS":"кв. м","SQUARE_KILOMETER":"квадратен километър","SQUARE_KILOMETERS":"квадратни километри","SQUARE_KILOMETER_TITLE":"Квадратни километри","SQUARE_KILOMETER_ABBR":"кв. км","SQUARE_KILOMETER_UNITS":"кв. км","SQUARE_MILE":"квадратна миля","SQUARE_MILES":"квадратни мили","SQUARE_MILE_TITLE":"Квадратни мили","SQUARE_MILE_ABBR":"кв. миля","SQUARE_MILE_UNITS":"кв. мили","ACRE":"акър","ACRES":"акра","ACRE_TITLE":"Акра","ACRE_ABBR":"акр.","ACRE_UNITS":"акра","HECTARE":"хектар","HECTARES":"хектари","HECTARE_TITLE":"Хектари","HECTARE_ABBR":"ха","HECTARE_UNITS":"ха"},"variables":{"standardSource":"Стандартни данни","customSource":"Персонализирани данни","layersSource":"Данни за слоеве","averageShort":"Ср.","labelWithType":"${label} (${type})","count":"Брой","index":"Индекс","percent":"Процент","average":"Средна","median":"Медиана","percapita":"На глава","density":"Плътност","rate":"Скорост на възпроизвеждане","ratio":"Съотношение","reliability":"Наличност и точност на данните","text":"Текст","area":"Площ","segmentation":"Сегментиране"}}