{"configureTimeSeries":"Konfiguriraj časovne nize","stepperHeadings":{"chooseFields":"Izberi polja","setTimeInterval":"Določi časovni interval","review":"Pregled"},"chooseFieldOptions":"Izberi možnosti polja","listItemOptions":{"prefixLabel":"Po predponi polja","prefixDescription":"Dodajte polja na temelju deljene predpone imenovanja.","manualLabel":"Ročno","manualDescription":"S seznama polja ročno izberite polja časovnih nizov."},"selectFields":"Izberi polja","addFields":"Dodaj polja","clearFields":"Počisti polja","clearSelection":"Počisti izbiro","prefixPlaceholder":"Pr: leto-dogodka","previewFields":"Polja predogleda","previewFieldsWithNumber":"Polja predogleda (${number})","noFieldsFound":"Najdena niso bila nobena polja z navedeno predpono.","go":"Pojdi","timeSeriesFields":"Polja časovnih nizov","noTimeSeriesFieldsTitle":"Ni še nobenih polj časovnih nizov","noTimeSeriesFieldsDescription":"Za začetek dodajte polja, ki ustrezajo različnim časovnim razponom.","noTimeSeriesFieldsDescriptionLong":"Za začetek dodajte polja, ki ustrezajo različnim časovnim razponom. Dve ali več vaših polj morajo predstavljati iste atribute podatkov v različnih časovnih točkah za vsak geoobjekt.","timeSeriesDoc":"Za navodila o vizualizacijah časovnih nizov obiščite {helpDoc}.","timeSeriesDocLink":"dokumentacija za pomoč","chooseTimeInterval":"Izberi časovni interval","timeUnit":"Časovna enota","startDate":"Začetni datum","startDateAndTime":"Začetni datum in čas","yearOnlyPlaceholder":"Vnesi leto","monthOnlyPlaceholder":"MM/LLLL","month":"Mesec","months":{"january":"Januar","february":"Februar","march":"Marec","april":"April","may":"Maj","june":"Junij","july":"Julij","august":"Avgust","september":"September","october":"Oktober","november":"November","december":"December"},"timeUnits":{"centuries":"Stoletje","decades":"Desetletje","years":"Leto","months":"Mesec","weeks":"Teden","days":"Dan","hours":"Ura","minutes":"Minuta","seconds":"Sekunda","milliseconds":"Milisekunda"},"timeZone":"Časovni pas","fieldTimeRange":"Razpon polja/časa","remove":"Odstrani","back":"Nazaj","cancel":"Prekliči","next":"Naprej","done":"Končano"}